odoo8_addon_l10n_es_payment_order_confirming_sabadell-8.0.1.0.0.99.dev3-py3.6-nspkg.pth
odoo_addons/l10n_es_payment_order_confirming_sabadell/README.rst
odoo_addons/l10n_es_payment_order_confirming_sabadell/__init__.py
odoo_addons/l10n_es_payment_order_confirming_sabadell/__openerp__.py
odoo_addons/l10n_es_payment_order_confirming_sabadell/data/payment_type_data.xml
odoo_addons/l10n_es_payment_order_confirming_sabadell/i18n/ca.po
odoo_addons/l10n_es_payment_order_confirming_sabadell/i18n/es.po
odoo_addons/l10n_es_payment_order_confirming_sabadell/i18n/l10n_es_payment_order_confirming_sabadell.pot
odoo_addons/l10n_es_payment_order_confirming_sabadell/models/__init__.py
odoo_addons/l10n_es_payment_order_confirming_sabadell/models/payment_mode.py
odoo_addons/l10n_es_payment_order_confirming_sabadell/static/description/icon.png
odoo_addons/l10n_es_payment_order_confirming_sabadell/views/payment_mode_view.xml
odoo_addons/l10n_es_payment_order_confirming_sabadell/wizard/__init__.py
odoo_addons/l10n_es_payment_order_confirming_sabadell/wizard/confirming_sabadell.py
odoo_addons/l10n_es_payment_order_confirming_sabadell/wizard/export_csb.py
odoo8_addon_l10n_es_payment_order_confirming_sabadell-8.0.1.0.0.99.dev3.dist-info/METADATA
odoo8_addon_l10n_es_payment_order_confirming_sabadell-8.0.1.0.0.99.dev3.dist-info/WHEEL
odoo8_addon_l10n_es_payment_order_confirming_sabadell-8.0.1.0.0.99.dev3.dist-info/namespace_packages.txt
odoo8_addon_l10n_es_payment_order_confirming_sabadell-8.0.1.0.0.99.dev3.dist-info/top_level.txt
odoo8_addon_l10n_es_payment_order_confirming_sabadell-8.0.1.0.0.99.dev3.dist-info/RECORD
